alehundred_depot-8.5.dist-info/licenses/LICENSE
alehundred_depot_en/__init__.py
alehundred_depot_en/main.py
alehundred_depot_en/p4_manager.py
alehundred_depot_en/tui.py
alehundred_depot_en/tui_help.py
alehundred_depot_en/tui_status.py
alehundred_depot_en/tui_user.py
alehundred_depot_en/utils.py
alehundred_depot-8.5.dist-info/METADATA
alehundred_depot-8.5.dist-info/WHEEL
alehundred_depot-8.5.dist-info/entry_points.txt
alehundred_depot-8.5.dist-info/top_level.txt
alehundred_depot-8.5.dist-info/RECORD
