Metadata-Version: 2.4
Name: alehundred-depot
Version: 8.5
Summary: A TUI tool to install and manage a Perforce server on a Raspberry Pi.
Author-email: Alejandro Friant <friant2021@gmail.com>
License: MIT License
Project-URL: Homepage, https://github.com/alefriant/Alehundred-VCS-Toolkit/tree/main
Project-URL: Bug Tracker, https://github.com/alefriant/Alehundred-VCS-Toolkit/issues
Classifier: Programming Language :: Python :: 3
Classifier: License :: OSI Approved :: MIT License
Classifier: Operating System :: POSIX :: Linux
Classifier: Environment :: Console :: Curses
Classifier: Topic :: Software Development :: Version Control
Classifier: Topic :: System :: Installation/Setup
Requires-Python: >=3.7
License-File: LICENSE
Requires-Dist: requests
Dynamic: license-file
